[
  {
    "id": "mex-taco-rice",
    "title": { "ko": "타코라이스", "ja": "タコライス" },
    "category": "멕시칸",
    "baseServings": 2,
    "time": { "prepMin": 10, "cookMin": 15 },
    "difficulty": "easy",
    "tags": ["한그릇", "밥", "고기"],
    "ingredients": [
      { "name": { "ko": "따뜻한 밥", "ja": "ご飯" }, "amount": 400, "unit": "g", "scaleType": "linear" },
      { "name": { "ko": "다진 고기(소·돼지 혼합)", "ja": "合いびき肉" }, "amount": 200, "unit": "g", "scaleType": "linear" },
      { "name": { "ko": "양파", "ja": "玉ねぎ" }, "amount": 0.5, "unit": "개", "scaleType": "count", "roundStep": 0.5 },
      { "name": { "ko": "양상추", "ja": "レタス" }, "amount": 100, "unit": "g", "scaleType": "linear" },
      { "name": { "ko": "토마토", "ja": "トマト" }, "amount": 1, "unit": "개", "scaleType": "count" },
      { "name": { "ko": "슈레드 치즈", "ja": "ピザ用チーズ" }, "amount": 50, "unit": "g", "scaleType": "linear" },
      { "name": { "ko": "케첩", "ja": "ケチャップ" }, "amount": 2, "unit": "큰술", "scaleType": "linear" },
      { "name": { "ko": "우스터소스", "ja": "ウスターソース" }, "amount": 1, "unit": "큰술", "scaleType": "linear" },
      { "name": { "ko": "칠리파우더(또는 타코 시즈닝)", "ja": "チリパウダー" }, "amount": 1, "unit": "작은술", "scaleType": "sqrt", "note": "업무슈퍼·카르디. 없으면 카레가루+고춧가루 소량으로 대체", "noteJa": "業務スーパーやカルディで。なければカレー粉+粉唐辛子少々で代用" },
      { "name": { "ko": "다진 마늘", "ja": "おろしにんにく" }, "amount": 1, "unit": "작은술", "scaleType": "sqrt" },
      { "name": { "ko": "소금·후추", "ja": "塩こしょう" }, "amount": null, "unit": "적당량", "scaleType": "to-taste" },
      { "name": { "ko": "살사·타바스코", "ja": "サルサ/タバスコ" }, "amount": null, "unit": "적당량", "scaleType": "to-taste", "optional": true }
    ],
    "steps": [
      "양파는 잘게 다지고, 양상추는 5mm 폭으로 채썬다. 토마토는 사방 1cm로 깍둑 썬다.",
      "팬에 다진 마늘·양파를 중불에서 투명해질 때까지 1~2분 볶는다.",
      "다진 고기를 넣고 색이 완전히 변할 때까지 볶으며 기름이 나오면 살짝 따라낸다.",
      "케첩·우스터소스·칠리파우더·소금·후추를 넣고 중불에서 2~3분, 국물이 자작해질 때까지 조려 타코미트를 만든다.",
      "그릇에 밥을 깔고 양상추 → 타코미트 → 토마토 → 치즈 순으로 올린다.",
      "취향에 따라 살사나 타바스코를 뿌린다."
    ],
    "stepsJa": [
      "玉ねぎはみじん切り、レタスは5mm幅の千切り、トマトは1cm角に切る。",
      "フライパンでおろしにんにくと玉ねぎを中火で1〜2分、透き通るまで炒める。",
      "合いびき肉を加え、色が完全に変わるまで炒め、脂が出たら軽く拭き取る。",
      "ケチャップ・ウスターソース・チリパウダー・塩こしょうを加え、中火で2〜3分、汁けが少なくなるまで煮詰めてタコミートを作る。",
      "器にご飯を敷き、レタス→タコミート→トマト→チーズの順にのせる。",
      "お好みでサルサやタバスコをかける。"
    ],
    "tips": [
      "오키나와발 대중식이라 일본 슈퍼 재료로 가장 쉽게 만드는 멕시칸. 또띠야 없이 밥으로.",
      "치즈를 따뜻한 밥·미트 위에 올리면 살짝 녹아 더 맛있다."
    ],
    "tipsJa": [
      "沖縄発の定番で、日本のスーパー食材でいちばん手軽に作れるメキシカン。トルティーヤ不要でご飯に。",
      "チーズを温かいご飯とミートの上にのせると少し溶けておいしい。"
    ]
  },
  {
    "id": "mex-tacos",
    "title": { "ko": "타코스", "ja": "タコス" },
    "category": "멕시칸",
    "baseServings": 2,
    "time": { "prepMin": 15, "cookMin": 15 },
    "difficulty": "normal",
    "tags": ["한그릇", "고기", "손님상"],
    "ingredients": [
      { "name": { "ko": "토르티야(소프트)", "ja": "トルティーヤ" }, "amount": 6, "unit": "장", "scaleType": "count", "note": "업무슈퍼·카르디. 옥수수/밀 둘 다 가능", "noteJa": "業務スーパー・カルディ。コーン/小麦どちらでも" },
      { "name": { "ko": "다진 고기(소·돼지 혼합)", "ja": "合いびき肉" }, "amount": 200, "unit": "g", "scaleType": "linear" },
      { "name": { "ko": "양파", "ja": "玉ねぎ" }, "amount": 0.5, "unit": "개", "scaleType": "count", "roundStep": 0.5 },
      { "name": { "ko": "양상추", "ja": "レタス" }, "amount": 80, "unit": "g", "scaleType": "linear" },
      { "name": { "ko": "토마토", "ja": "トマト" }, "amount": 1, "unit": "개", "scaleType": "count" },
      { "name": { "ko": "슈레드 치즈", "ja": "ピザ用チーズ" }, "amount": 60, "unit": "g", "scaleType": "linear" },
      { "name": { "ko": "칠리파우더", "ja": "チリパウダー" }, "amount": 1, "unit": "작은술", "scaleType": "sqrt" },
      { "name": { "ko": "쿠민(선택)", "ja": "クミン" }, "amount": 0.5, "unit": "작은술", "scaleType": "sqrt", "optional": true },
      { "name": { "ko": "다진 마늘", "ja": "おろしにんにく" }, "amount": 1, "unit": "작은술", "scaleType": "sqrt" },
      { "name": { "ko": "케첩", "ja": "ケチャップ" }, "amount": 1, "unit": "큰술", "scaleType": "linear" },
      { "name": { "ko": "소금·후추", "ja": "塩こしょう" }, "amount": null, "unit": "적당량", "scaleType": "to-taste" },
      { "name": { "ko": "라임·고수(선택)", "ja": "ライム・パクチー" }, "amount": null, "unit": "적당량", "scaleType": "to-taste", "optional": true }
    ],
    "steps": [
      "양파는 잘게 다지고, 양상추는 채썰고, 토마토는 사방 1cm로 깍둑 썬다.",
      "팬에 다진 마늘·양파를 볶다가 다진 고기를 넣어 색이 변할 때까지 중불에 볶는다.",
      "칠리파우더·쿠민·케첩·소금·후추를 넣고 2~3분 조려 타코미트를 만든다.",
      "토르티야는 마른 팬에 양면을 20~30초씩 데워 부드럽게 한다.",
      "토르티야에 양상추 → 타코미트 → 토마토 → 치즈를 올리고 반으로 접는다.",
      "라임을 짜고 고수를 올려 먹는다."
    ],
    "stepsJa": [
      "玉ねぎはみじん切り、レタスは千切り、トマトは1cm角に切る。",
      "フライパンでおろしにんにくと玉ねぎを炒め、合いびき肉を加えて中火で色が変わるまで炒める。",
      "チリパウダー・クミン・ケチャップ・塩こしょうを加え、2〜3分煮詰めてタコミートを作る。",
      "トルティーヤは油をひかないフライパンで両面20〜30秒ずつ温めてやわらかくする。",
      "トルティーヤにレタス→タコミート→トマト→チーズをのせ、半分に折る。",
      "ライムを絞り、パクチーをのせて食べる。"
    ],
    "tips": [
      "토르티야는 데워야 갈라지지 않고 잘 접힌다.",
      "속재료는 각자 싸 먹게 따로 담아내면 파티용으로도 좋다."
    ],
    "tipsJa": [
      "トルティーヤは温めると割れず、きれいに折れる。",
      "具を別々に盛って各自で巻けば、パーティーにもぴったり。"
    ]
  },
  {
    "id": "mex-quesadilla",
    "title": { "ko": "케사디야", "ja": "ケサディーヤ" },
    "category": "멕시칸",
    "baseServings": 2,
    "time": { "prepMin": 10, "cookMin": 10 },
    "difficulty": "easy",
    "tags": ["한그릇", "치즈", "간편"],
    "ingredients": [
      { "name": { "ko": "토르티야", "ja": "トルティーヤ" }, "amount": 4, "unit": "장", "scaleType": "count" },
      { "name": { "ko": "슈레드 치즈", "ja": "ピザ用チーズ" }, "amount": 120, "unit": "g", "scaleType": "linear", "note": "많을수록 잘 붙는다", "noteJa": "多いほどよくくっつく" },
      { "name": { "ko": "닭고기(또는 햄)", "ja": "鶏肉/ハム" }, "amount": 120, "unit": "g", "scaleType": "linear", "optional": true },
      { "name": { "ko": "피망·파프리카", "ja": "ピーマン/パプリカ" }, "amount": 1, "unit": "개", "scaleType": "count", "optional": true },
      { "name": { "ko": "양파", "ja": "玉ねぎ" }, "amount": 0.5, "unit": "개", "scaleType": "count", "roundStep": 0.5, "optional": true },
      { "name": { "ko": "식용유", "ja": "サラダ油" }, "amount": 0.5, "unit": "큰술", "scaleType": "fixed" },
      { "name": { "ko": "살사·사워크림(선택)", "ja": "サルサ/サワークリーム" }, "amount": null, "unit": "적당량", "scaleType": "to-taste", "optional": true }
    ],
    "steps": [
      "닭고기·피망·양파는 잘게 썰어 기름 두른 팬에 익힌 뒤 덜어 둔다.",
      "토르티야 한 장의 반쪽에 치즈를 뿌리고 속재료를 올린 뒤 다시 치즈를 조금 얹는다.",
      "반으로 접어 약불~중불 팬에 앞뒤로 2~3분씩, 노릇하고 치즈가 녹을 때까지 굽는다.",
      "도마에서 한 김 식힌 뒤 피자처럼 3~4등분으로 썬다.",
      "살사나 사워크림을 곁들인다."
    ],
    "stepsJa": [
      "鶏肉・ピーマン・玉ねぎは小さく切り、油をひいたフライパンで火を通して取り出す。",
      "トルティーヤ1枚の片側にチーズを散らし、具をのせて、さらにチーズを少しのせる。",
      "半分に折り、弱〜中火のフライパンで両面2〜3分ずつ、こんがりしてチーズが溶けるまで焼く。",
      "まな板で少し冷ましてから、ピザのように3〜4等分に切る。",
      "サルサやサワークリームを添える。"
    ],
    "tips": [
      "치즈가 접착제 역할 — 가장자리에도 조금 뿌리면 잘 붙는다.",
      "속을 비우고 치즈만 넣어도 훌륭한 간식·안주."
    ],
    "tipsJa": [
      "チーズが接着剤の役目 — 端にも少し散らすとくっつきやすい。",
      "具なしでチーズだけでも立派なおやつ・おつまみに。"
    ]
  },
  {
    "id": "mex-guacamole",
    "title": { "ko": "과카몰리", "ja": "ワカモレ" },
    "category": "멕시칸",
    "baseServings": 2,
    "time": { "prepMin": 10, "cookMin": 0 },
    "difficulty": "easy",
    "tags": ["다이어트", "저탄수", "아보카도", "사이드"],
    "ingredients": [
      { "name": { "ko": "아보카도", "ja": "アボカド" }, "amount": 2, "unit": "개", "scaleType": "count", "note": "말랑하게 잘 익은 것", "noteJa": "やわらかく熟したもの" },
      { "name": { "ko": "양파", "ja": "玉ねぎ" }, "amount": 40, "unit": "g", "scaleType": "linear", "note": "잘게 다져 찬물에 헹구면 매운맛↓", "noteJa": "みじん切りにして水にさらすと辛みが和らぐ" },
      { "name": { "ko": "토마토", "ja": "トマト" }, "amount": 0.5, "unit": "개", "scaleType": "count", "roundStep": 0.5 },
      { "name": { "ko": "라임즙(또는 레몬즙)", "ja": "ライム/レモン汁" }, "amount": 1, "unit": "큰술", "scaleType": "linear" },
      { "name": { "ko": "다진 마늘", "ja": "おろしにんにく" }, "amount": 1, "unit": "작은술", "scaleType": "sqrt", "optional": true },
      { "name": { "ko": "소금·후추", "ja": "塩こしょう" }, "amount": null, "unit": "적당량", "scaleType": "to-taste" },
      { "name": { "ko": "고수(선택)", "ja": "パクチー" }, "amount": null, "unit": "적당량", "scaleType": "to-taste", "optional": true }
    ],
    "steps": [
      "아보카도는 반 갈라 씨를 빼고 과육을 볼에 담아 포크로 원하는 정도로 으깬다.",
      "양파·토마토는 사방 5mm로 잘게 다진다.",
      "볼에 양파·토마토·라임즙·다진 마늘·소금·후추를 넣고 골고루 섞는다.",
      "고수를 뿌린다. 갈변을 막으려면 라임즙을 넉넉히, 표면에 랩을 밀착해 보관한다."
    ],
    "stepsJa": [
      "アボカドは半分に切って種を除き、果肉をボウルに入れてフォークで好みの粗さにつぶす。",
      "玉ねぎ・トマトは5mm角に細かく刻む。",
      "ボウルに玉ねぎ・トマト・ライム汁・おろしにんにく・塩こしょうを入れてよく混ぜる。",
      "パクチーを散らす。変色を防ぐにはライム汁を多めにし、表面にラップを密着させて保存する。"
    ],
    "tips": [
      "탄수화물이 적고 좋은 지방이 풍부한 저탄수 사이드. 토르티야칩·타코·빵에 두루 어울린다.",
      "라임즙이 갈변 방지와 상큼함을 동시에 잡는다."
    ],
    "tipsJa": [
      "糖質が少なく良質な脂質が豊富な低糖質サイド。トルティーヤチップス・タコス・パンに合う。",
      "ライム汁が変色防止とさわやかさを同時にかなえる。"
    ]
  },
  {
    "id": "mex-chili-con-carne",
    "title": { "ko": "칠리 콘 카르네", "ja": "チリコンカン" },
    "category": "멕시칸",
    "baseServings": 2,
    "time": { "prepMin": 10, "cookMin": 25 },
    "difficulty": "normal",
    "tags": ["국물", "콩", "고기"],
    "ingredients": [
      { "name": { "ko": "다진 소고기", "ja": "牛ひき肉" }, "amount": 200, "unit": "g", "scaleType": "linear" },
      { "name": { "ko": "믹스빈스(강낭콩 캔)", "ja": "ミックスビーンズ/金時豆缶" }, "amount": 150, "unit": "g", "scaleType": "linear", "note": "일반슈퍼·업무슈퍼 캔·팩", "noteJa": "スーパー・業務スーパーの缶/パック" },
      { "name": { "ko": "양파", "ja": "玉ねぎ" }, "amount": 1, "unit": "개", "scaleType": "count" },
      { "name": { "ko": "토마토 통조림", "ja": "カットトマト缶" }, "amount": 200, "unit": "g", "scaleType": "linear" },
      { "name": { "ko": "마늘", "ja": "にんにく" }, "amount": 2, "unit": "쪽", "scaleType": "count" },
      { "name": { "ko": "칠리파우더", "ja": "チリパウダー" }, "amount": 1, "unit": "작은술", "scaleType": "sqrt" },
      { "name": { "ko": "쿠민(선택)", "ja": "クミン" }, "amount": 0.5, "unit": "작은술", "scaleType": "sqrt", "optional": true },
      { "name": { "ko": "케첩", "ja": "ケチャップ" }, "amount": 1, "unit": "큰술", "scaleType": "linear" },
      { "name": { "ko": "콘소메(고형)", "ja": "コンソメ" }, "amount": 1, "unit": "개", "scaleType": "count" },
      { "name": { "ko": "올리브유", "ja": "オリーブオイル" }, "amount": 1, "unit": "큰술", "scaleType": "fixed" },
      { "name": { "ko": "소금·후추", "ja": "塩こしょう" }, "amount": null, "unit": "적당량", "scaleType": "to-taste" }
    ],
    "steps": [
      "양파는 사방 1cm로 깍둑 썰고, 마늘은 다진다. 콩 캔은 체에 밭쳐 물기를 뺀다.",
      "냄비에 올리브유를 두르고 마늘·양파를 중불에서 투명해질 때까지 볶는다.",
      "다진 소고기를 넣어 색이 변할 때까지 볶고, 칠리파우더·쿠민을 넣어 30초 볶아 향을 낸다.",
      "토마토 통조림·케첩·콘소메·콩을 넣고 물이 부족하면 조금 더해 끓인다.",
      "뚜껑을 반쯤 덮고 중약불로 15~20분, 걸쭉해질 때까지 조린다.",
      "소금·후추로 간한다. 밥·빵·토르티야칩 어디에나 어울린다."
    ],
    "stepsJa": [
      "玉ねぎは1cm角に切り、にんにくはみじん切りにする。豆の缶はざるに上げて水気を切る。",
      "鍋にオリーブオイルをひき、にんにく・玉ねぎを中火で透き通るまで炒める。",
      "牛ひき肉を加えて色が変わるまで炒め、チリパウダー・クミンを入れて30秒炒めて香りを出す。",
      "カットトマト缶・ケチャップ・コンソメ・豆を加え、水が足りなければ少し足して煮る。",
      "蓋を半分ずらしてのせ、中弱火で15〜20分、とろりとするまで煮込む。",
      "塩こしょうで味を調える。ご飯・パン・トルティーヤチップスに合う。"
    ],
    "tips": [
      "매운맛은 칠리파우더 양으로 조절. 오래 조릴수록 맛이 진해진다.",
      "밥에 얹으면 칠리라이스, 치즈를 올리면 더 든든하다."
    ],
    "tipsJa": [
      "辛さはチリパウダーの量で調整。長く煮込むほど味が濃くなる。",
      "ご飯にのせればチリライス、チーズをのせればさらにボリューム満点。"
    ]
  }
]
